<?xml version="1.0" encoding="UTF-8"?>
<!DOCTYPE suite SYSTEM "http://testng.org/testng-1.0.dtd">
<suite name="Railway Testcase" parallel="classes">
    <parameter name="path" value="\driver\msedgedriver.exe"/>
    <parameter name="browser" value="edge"/>
    <test name="Set 1">
        <classes>
            <class name="testcase.TC01"></class>
            <class name="testcase.TC02"></class>
            <class name="testcase.TC03"></class>
            <class name="testcase.TC04"></class>
            <class name="testcase.TC05"></class>
            <class name="testcase.TC06"></class>
            <class name="testcase.TC07"></class>
            <class name="testcase.TC08"></class>
            <class name="testcase.TC09"></class>
            <class name="testcase.TC10"></class>
            <class name="testcase.TC11"></class>
            <class name="testcase.TC12"></class>
            <class name="testcase.TC13"></class>
            <class name="testcase.TC14"></class>
            <class name="testcase.TC15"></class>
            <class name="testcase.TC16"></class>
        </classes>
    </test>
</suite>